{
  "aca" : [ "lexlocation", "lexposition" ],
  "accion" : [ "lexactions", "lexurgentrequests" ],
  "actual" : [ "lexdaily", "lexpositive" ],
  "acumula" : [ "lexactions", "lexapplies" ],
  "ademas" : [ "lexaddition", "lexadverbs", "lexconjunctions", "lexpositive" ],
  "advertencia" : [ "lexalerts", "lexspamalerts" ],
  "agenda" : [ "lexnotifications", "lexplanning" ],
  "agregada" : [ "lexaddition", "lexadditional" ],
  "agregalos" : [ "lexactions", "lexcommerce" ],
  "ahora" : [ "lexdaily", "lexurgentrequests" ],
  "alcance" : [ "lexrange", "lexreach" ],
  "alerta" : [ "lexalerts", "lexnotifications" ],
  "alterar" : [ "lexactions", "lexchange" ],
  "amplia" : [ "lexexpansion", "lexpositive" ],
  "anuncio" : [ "lexmarketing", "lexnotifications" ],
  "aplicacion" : [ "lexapplications", "lexwebactions" ],
  "aplicaran" : [ "lexconstraints", "lexregulations" ],
  "aqui" : [ "lexhelp", "lexlocation" ],
  "asi" : [ "lexadverbs", "lexconjunctions" ],
  "aun" : [ "contextualLexeme", "lexhelp" ],
  "autenticacion" : [ "lexsecurity", "lextechnology" ],
  "automatica" : [ "lexautomation", "lextechnology" ],
  "automaticamente" : [ "lexautomation", "lextechnology" ],
  "balanceadores" : [ "lexfinance", "lextechnology" ],
  "bancaria" : [ "lexfinance", "lexhealth" ],
  "bancarias" : [ "lexfinance", "lexhealth" ],
  "basilicas" : [ "lexcontextual", "lexreligion" ],
  "bitcoin" : [ "lexcurrencies", "lexfinance" ],
  "bloque" : [ "lexsecurity", "lexstructure" ],
  "bodas" : [ "lexcelebration", "lexevents" ],
  "boletin" : [ "lexdocuments", "lexsubscriptions" ],
  "boletines" : [ "lexcommunication", "lexmarketing" ],
  "boletos" : [ "lexmarketing", "lextravel" ],
  "bonificacion" : [ "lexfinance", "lexpromotions" ],
  "bonificados" : [ "lexfinance", "lexpromotions" ],
  "bonificara" : [ "lexfinance", "lexpromotions" ],
  "borrar" : [ "lexactions", "lexsecurity" ],
  "boton" : [ "lextechnology", "lexuiux" ],
  "broadway" : [ "lexcontextual", "lexentertainment" ],
  "buenos" : [ "lexlocation", "lexpositive" ],
  "cafe" : [ "lexdaily", "lexfood", "lexproducts" ],
  "catalogo" : [ "lexcommerce", "lexproducts" ],
  "cinco" : [ "lexnum", "lexnumbers" ],
  "clic" : [ "lexactions", "lextechnology" ],
  "cliche" : [ "lexcommunication", "lexexpression" ],
  "codigo" : [ "lexcodes", "lextechnology" ],
  "compra" : [ "lexcommerce", "lexpurchase", "lexpurchases" ],
  "consegui" : [ "lexactions", "lexobtaining" ],
  "consultas" : [ "lexdocuments", "lexfeedback" ],
  "contratacion" : [ "lexemployment", "lexwork" ],
  "credito" : [ "lexbanking", "lexfinance" ],
  "cuando" : [ "lexadverbs", "lextime" ],
  "cuatro" : [ "lexnum", "lexnumbers" ],
  "desarrollo" : [ "leximprovements", "lexsteps" ],
  "developer" : [ "lexemployment", "lextechnology" ],
  "dia" : [ "lexdaily", "lexfrequency" ],
  "diez" : [ "lexnum", "lexnumbers" ],
  "diferente" : [ "lexdifferences", "lexopposites" ],
  "direccion" : [ "lexcontact", "lexlocation", "lexnetworking" ],
  "distribucion" : [ "lexdistribution", "lexstatistics" ],
  "donde" : [ "lexadverbs", "lexquestions" ],
  "dos" : [ "lexnum", "lexnumbers" ],
  "el" : [ "lexdeterminers", "lexpronouns" ],
  "electronico" : [ "lexcommunication", "lextechnology" ],
  "elegi" : [ "lexactions", "lexchoices" ],
  "eminent" : [ "lexqualities", "lexstatus", "lexsuperlatives" ],
  "emision" : [ "lexcommunication", "lexfinance" ],
  "entrena" : [ "lexpractice", "lextraining" ],
  "ese" : [ "contextualLexeme", "lexdeterminers" ],
  "euros" : [ "lexcurrency", "lexeconomy" ],
  "eventos" : [ "lexevents", "lextravel" ],
  "formaciones" : [ "lexeducation", "lextraining" ],
  "ganado" : [ "lexpositive", "lexqualities" ],
  "guia" : [ "lexcodes", "lexguidelines", "lexsteps" ],
  "incompatible" : [ "lexcompatibility", "lexopposites" ],
  "increibles" : [ "lexintensity", "lexpositive" ],
  "informacion" : [ "lexdocuments", "lexinformative" ],
  "inscripcion" : [ "lexregistration", "lexsubscriptions" ],
  "instrucciones" : [ "lexdocuments", "lexinstructions", "lexsteps" ],
  "interes" : [ "lexcontextual", "lexfinance" ],
  "interesa" : [ "lexcontextual", "lexpositive" ],
  "invalidNumber" : [ "lexerrors", "lexvalidation" ],
  "invertido" : [ "lexinvestment", "lexopposites" ],
  "kilos" : [ "lexdimensions", "lexweight" ],
  "lectura" : [ "lexeducation", "lexreading" ],
  "limpieza" : [ "lexhousehold", "lexnotifications" ],
  "maneja" : [ "lexactions", "lexmanagement" ],
  "manejas" : [ "lexactions", "lexmanagement" ],
  "mas" : [ "lexadverbs", "lexcomparisons", "lexconjunctions" ],
  "mascota" : [ "lexanimals", "lexcelebration" ],
  "metodo" : [ "lexinstructions", "lexsteps" ],
  "minimo" : [ "lexconstraints", "lexmeasurement", "lexminimum" ],
  "movil" : [ "lexmobile", "lextelecom" ],
  "noticias" : [ "lexinformative", "lexnews" ],
  "novedades" : [ "leximprovements", "lexnotifications" ],
  "nueve" : [ "lexnum", "lexnumbers" ],
  "o" : [ "lexconjunctions", "lexsymbols" ],
  "ocho" : [ "lexnum", "lexnumbers" ],
  "operacion" : [ "lexoperations", "lexwork" ],
  "operativa" : [ "lexoperations", "lexwork" ],
  "opuesto" : [ "lexcontrast", "lexopposites" ],
  "paises" : [ "lexcountries", "lexlocation" ],
  "pascuas" : [ "lexcelebration", "lexevents" ],
  "pequenos" : [ "lexquantities", "lexsize" ],
  "plataforma" : [ "lexcommerce", "lexurls" ],
  "podriamos" : [ "lexcapability", "lexpossibilities" ],
  "policia" : [ "lexlaw", "lexsecurity" ],
  "potencial" : [ "lexgrowth", "lexqualities" ],
  "prestamos" : [ "lexbanking", "lexfinance" ],
  "prioritariamente" : [ "lexneutral", "lexurgency" ],
  "proceso" : [ "lexsteps", "lextracking" ],
  "proteccion" : [ "lexprotection", "lexsecurity" ],
  "rapido" : [ "lexqualities", "lexspeed" ],
  "realidad" : [ "lexemotion", "lextechnology" ],
  "reintegros" : [ "lexbenefits", "lexfinance" ],
  "reserva" : [ "lexevents", "lextracking" ],
  "ruta" : [ "lexdaily", "lexsteps" ],
  "seis" : [ "lexnum", "lexnumbers" ],
  "sesion" : [ "lexsession", "lexsessions" ],
  "si" : [ "lexadverbs", "lexconjunctions" ],
  "siete" : [ "lexnum", "lexnumbers" ],
  "sin" : [ "lexmarketing", "lexprepositions" ],
  "solo" : [ "lexadverbs", "lexmarketing" ],
  "suma" : [ "lexaddition", "lexadditional" ],
  "tecnologia" : [ "lexsector", "lextechnology" ],
  "telefonica" : [ "lextelecom", "lextelephony" ],
  "tenes" : [ "lexauxiliaryverbs", "lexrequests" ],
  "terminos" : [ "lexguidelines", "lexlegal" ],
  "them" : [ "lexnames", "lexpronouns" ],
  "todavia" : [ "lexadverbs", "lextime" ],
  "trabajo" : [ "lexdaily", "lexwork" ],
  "tres" : [ "lexnum", "lexnumbers" ],
  "trusted" : [ "lexpositive", "lextrust" ],
  "ultima" : [ "lexsuperlatives", "lexurgency" ],
  "ultimas" : [ "lexdeterminers", "lexnews" ],
  "unico" : [ "lexexclusive", "lexvaluable" ],
  "unicos" : [ "lexqualities", "lexsuperlatives" ],
  "uno" : [ "lexnum", "lexnumbers" ],
  "verificacion" : [ "lextests", "lexvalidation" ],
  "videos" : [ "lexentertainment", "lexmedia" ],
  "vision" : [ "lexcommunication", "lexeducation" ],
  "ya" : [ "lexadverbs", "lextime" ],
  "“" : [ "lexformatting", "lexpunctuation" ],
  "“””" : [ "lexformatting", "lexpunctuation", "lexsymbols" ],
  "”" : [ "lexformatting", "lexpunctuation" ]
}